setup.py
commons/__init__.py
commons/configure.py
commons/data_provider.py
commons/data_storer.py
commons/hdfs_data_loader.py
commons/np_commons.py
commons/registry.py
commons/stats.py
commons/tasker.py
commons/testing.py
commons/tmpfile.py
commons/utils.py
py_commons.egg-info/PKG-INFO
py_commons.egg-info/SOURCES.txt
py_commons.egg-info/dependency_links.txt
py_commons.egg-info/pbr.json
py_commons.egg-info/requires.txt
py_commons.egg-info/top_level.txt