Metadata-Version: 1.0
Name: py-commons
Version: 0.1.2
Summary: A set of useful utils for data analysis
Home-page: UNKNOWN
Author: Data Science
Author-email: DataScience@pulsepoint.com
License: UNKNOWN
Platform: UNKNOWN
